{
    "op_type": "ForeachMulList",
    "op_list": [
        {
            "bin_filename": "ForeachMulList_ed7caf0e9926346742eca5bf740dd55c",
            "inputs": [
                [
                    {
                        "name": "x1",
                        "index": 0,
                        "dtype": "float16",
                        "format": "ND",
                        "paramType": "dynamic",
                        "shape": [
                            -2
                        ]
                    }
                ],
                [
                    {
                        "name": "x2",
                        "index": 1,
                        "dtype": "float16",
                        "format": "ND",
                        "paramType": "dynamic",
                        "shape": [
                            -2
                        ]
                    }
                ]
            ],
            "outputs": [
                [
                    {
                        "name": "y",
                        "index": 0,
                        "dtype": "float16",
                        "format": "ND",
                        "paramType": "dynamic",
                        "shape": [
                            -2
                        ]
                    }
                ]
            ]
        },
        {
            "bin_filename": "ForeachMulList_4a6ebd76fd96690db2da8ea99d998914",
            "inputs": [
                [
                    {
                        "name": "x1",
                        "index": 0,
                        "dtype": "float32",
                        "format": "ND",
                        "paramType": "dynamic",
                        "shape": [
                            -2
                        ]
                    }
                ],
                [
                    {
                        "name": "x2",
                        "index": 1,
                        "dtype": "float32",
                        "format": "ND",
                        "paramType": "dynamic",
                        "shape": [
                            -2
                        ]
                    }
                ]
            ],
            "outputs": [
                [
                    {
                        "name": "y",
                        "index": 0,
                        "dtype": "float32",
                        "format": "ND",
                        "paramType": "dynamic",
                        "shape": [
                            -2
                        ]
                    }
                ]
            ]
        },
        {
            "bin_filename": "ForeachMulList_87f682a7728fc3d0e4669f3b051f4706",
            "inputs": [
                [
                    {
                        "name": "x1",
                        "index": 0,
                        "dtype": "int32",
                        "format": "ND",
                        "paramType": "dynamic",
                        "shape": [
                            -2
                        ]
                    }
                ],
                [
                    {
                        "name": "x2",
                        "index": 1,
                        "dtype": "int32",
                        "format": "ND",
                        "paramType": "dynamic",
                        "shape": [
                            -2
                        ]
                    }
                ]
            ],
            "outputs": [
                [
                    {
                        "name": "y",
                        "index": 0,
                        "dtype": "int32",
                        "format": "ND",
                        "paramType": "dynamic",
                        "shape": [
                            -2
                        ]
                    }
                ]
            ]
        },
        {
            "bin_filename": "ForeachMulList_c1595d34c046d92e00dbfaab179eaa8d",
            "inputs": [
                [
                    {
                        "name": "x1",
                        "index": 0,
                        "dtype": "bfloat16",
                        "format": "ND",
                        "paramType": "dynamic",
                        "shape": [
                            -2
                        ]
                    }
                ],
                [
                    {
                        "name": "x2",
                        "index": 1,
                        "dtype": "bfloat16",
                        "format": "ND",
                        "paramType": "dynamic",
                        "shape": [
                            -2
                        ]
                    }
                ]
            ],
            "outputs": [
                [
                    {
                        "name": "y",
                        "index": 0,
                        "dtype": "bfloat16",
                        "format": "ND",
                        "paramType": "dynamic",
                        "shape": [
                            -2
                        ]
                    }
                ]
            ]
        }
    ]
}