{
  "op_type": "GroupedBiasAddGrad",
  "op_list": [
    {
      "bin_filename": "GroupedBiasAddGrad_acff02ed31ef1ec2c7e4e1b8c3eac622",
      "inputs": [
        {
          "name": "grad_y",
          "index": 0,
          "dtype": "bfloat16",
          "format": "ND",
          "paramType": "required",
          "shape": [
            -2
          ]
        },
        {
          "name": "group_idx",
          "index": 1,
          "dtype": "int32",
          "format": "ND",
          "paramType": "optional",
          "shape": [
            -2
          ]
        }
      ],
      "outputs": [
        {
          "name": "grad_bias",
          "index": 0,
          "dtype": "bfloat16",
          "format": "ND",
          "paramType": "required",
          "shape": [
            -2
          ]
        }
      ],
      "attrs": [
        {
          "name": "group_idx_type",
          "dtype": "int",
          "value": null
        }
      ]
    },
    {
      "bin_filename": "GroupedBiasAddGrad_7e5992d3033ef32a3463c5d198e518a1",
      "inputs": [
        {
          "name": "grad_y",
          "index": 0,
          "dtype": "bfloat16",
          "format": "ND",
          "paramType": "required",
          "shape": [
            -2
          ]
        },
        {
          "name": "group_idx",
          "index": 1,
          "dtype": "int64",
          "format": "ND",
          "paramType": "optional",
          "shape": [
            -2
          ]
        }
      ],
      "outputs": [
        {
          "name": "grad_bias",
          "index": 0,
          "dtype": "bfloat16",
          "format": "ND",
          "paramType": "required",
          "shape": [
            -2
          ]
        }
      ],
      "attrs": [
        {
          "name": "group_idx_type",
          "dtype": "int",
          "value": null
        }
      ]
    },
    {
      "bin_filename": "GroupedBiasAddGrad_5ce316c9f935f0585864b2d372bcc322",
      "inputs": [
        {
          "name": "grad_y",
          "index": 0,
          "dtype": "float16",
          "format": "ND",
          "paramType": "required",
          "shape": [
            -2
          ]
        },
        {
          "name": "group_idx",
          "index": 1,
          "dtype": "int32",
          "format": "ND",
          "paramType": "optional",
          "shape": [
            -2
          ]
        }
      ],
      "outputs": [
        {
          "name": "grad_bias",
          "index": 0,
          "dtype": "float16",
          "format": "ND",
          "paramType": "required",
          "shape": [
            -2
          ]
        }
      ],
      "attrs": [
        {
          "name": "group_idx_type",
          "dtype": "int",
          "value": null
        }
      ]
    },
    {
      "bin_filename": "GroupedBiasAddGrad_be837fe498fad076d01c0ce8dfd3d014",
      "inputs": [
        {
          "name": "grad_y",
          "index": 0,
          "dtype": "float16",
          "format": "ND",
          "paramType": "required",
          "shape": [
            -2
          ]
        },
        {
          "name": "group_idx",
          "index": 1,
          "dtype": "int64",
          "format": "ND",
          "paramType": "optional",
          "shape": [
            -2
          ]
        }
      ],
      "outputs": [
        {
          "name": "grad_bias",
          "index": 0,
          "dtype": "float16",
          "format": "ND",
          "paramType": "required",
          "shape": [
            -2
          ]
        }
      ],
      "attrs": [
        {
          "name": "group_idx_type",
          "dtype": "int",
          "value": null
        }
      ]
    },
    {
      "bin_filename": "GroupedBiasAddGrad_7538f6ca8b4e71ac38750eb26a539cca",
      "inputs": [
        {
          "name": "grad_y",
          "index": 0,
          "dtype": "float32",
          "format": "ND",
          "paramType": "required",
          "shape": [
            -2
          ]
        },
        {
          "name": "group_idx",
          "index": 1,
          "dtype": "int32",
          "format": "ND",
          "paramType": "optional",
          "shape": [
            -2
          ]
        }
      ],
      "outputs": [
        {
          "name": "grad_bias",
          "index": 0,
          "dtype": "float32",
          "format": "ND",
          "paramType": "required",
          "shape": [
            -2
          ]
        }
      ],
      "attrs": [
        {
          "name": "group_idx_type",
          "dtype": "int",
          "value": null
        }
      ]
    },
    {
      "bin_filename": "GroupedBiasAddGrad_9a632dc5b6be9e1b4215e3cf2b1aff0d",
      "inputs": [
        {
          "name": "grad_y",
          "index": 0,
          "dtype": "float32",
          "format": "ND",
          "paramType": "required",
          "shape": [
            -2
          ]
        },
        {
          "name": "group_idx",
          "index": 1,
          "dtype": "int64",
          "format": "ND",
          "paramType": "optional",
          "shape": [
            -2
          ]
        }
      ],
      "outputs": [
        {
          "name": "grad_bias",
          "index": 0,
          "dtype": "float32",
          "format": "ND",
          "paramType": "required",
          "shape": [
            -2
          ]
        }
      ],
      "attrs": [
        {
          "name": "group_idx_type",
          "dtype": "int",
          "value": null
        }
      ]
    }
  ]
}